xxt/__init__.py
xxt/funcs.py
xxt-0.0.6.dist-info/METADATA
xxt-0.0.6.dist-info/WHEEL
xxt-0.0.6.dist-info/top_level.txt
xxt-0.0.6.dist-info/RECORD
