Metadata-Version: 2.1
Name: xxt
Version: 0.0.6
Summary: XXT is a multifunctional Python library designed to enhance various aspects of programming by providing an extensive set of functions and classes
Home-page: https://pythonraft1575.github.io/xxt/
Author: Xi Teo
Author-email: diamondraft1575@gmail.com
License: MIT
Classifier: Intended Audience :: Developers
Classifier: License :: OSI Approved :: MIT License
Classifier: Programming Language :: Python
Classifier: Programming Language :: Python :: 3.11
Classifier: Operating System :: OS Independent
Requires-Dist: datetime
Requires-Dist: openai
Requires-Dist: qrcode
